jambazid/demo/__init__.py
jambazid/demo/data/schema.json
jambazid/demo/module.py
jambazid/demo/py.typed
jambazid/demo/subpackage/__init__.py
jambazid/demo/subpackage/submodule.py
jambazid_sftp-0.0.66.dist-info/METADATA
jambazid_sftp-0.0.66.dist-info/WHEEL
jambazid_sftp-0.0.66.dist-info/RECORD
