Metadata-Version: 2.3
Name: jambazid-sftp
Version: 0.0.66
Summary: A minimal Python project template built with Poetry.
License: MIT
Author: Jambazid PyPI
Author-email: pypi@jambazid.dev
Maintainer: Jambazid PyPI
Maintainer-email: pypi@jambazid.dev
Requires-Python: >=3.11,<4.0
Classifier: Development Status :: 2 - Pre-Alpha
Classifier: License :: OSI Approved :: MIT License
Classifier: Programming Language :: Python :: 3
Classifier: Programming Language :: Python :: 3.11
Classifier: Programming Language :: Python :: 3.12
Classifier: Programming Language :: Python :: 3.13
Classifier: Topic :: Documentation
Classifier: Topic :: Software Development :: Build Tools
Classifier: Topic :: Software Development :: Libraries :: Python Modules
Classifier: Topic :: Software Development :: Testing
Project-URL: Homepage, https://poetry-demo.python.jambazid.dev
Project-URL: Repository, https://github.com/jambazid/python-poetry-template
